ops_reactive_interface.py
ops_reactive_interface-1.1.0.dist-info/LICENSE
ops_reactive_interface-1.1.0.dist-info/METADATA
ops_reactive_interface-1.1.0.dist-info/WHEEL
ops_reactive_interface-1.1.0.dist-info/entry_points.txt
ops_reactive_interface-1.1.0.dist-info/top_level.txt
ops_reactive_interface-1.1.0.dist-info/RECORD
