Metadata-Version: 2.1
Name: ops_reactive_interface
Version: 1.1.0
Summary: Helper for interface APIs written for the charm operator framework, which can register them with charms.reactive to function similarly to Endpoints.
Home-page: https://github.com/juju-solutions/ops-reactive-interface
Author: Cory Johns
Author-email: cory.johns@canonical.com
License: Apache License 2.0
License-File: LICENSE
Requires-Dist: ops>=1.0.0
